pybrary/__init__.py
pybrary/constants.py
pybrary/volume.json
pybrary/api/__init__.py
pybrary/api/pybrary.py
pybrary/curation/__init__.py
pybrary/curation/curation.py
pybrary/databrary/__init__.py
pybrary/databrary/asset.py
pybrary/databrary/condition.py
pybrary/databrary/container.py
pybrary/databrary/context.py
pybrary/databrary/exclusion.py
pybrary/databrary/group.py
pybrary/databrary/participant.py
pybrary/databrary/pilot.py
pybrary/databrary/record.py
pybrary/databrary/recordFactory.py
pybrary/databrary/task.py
pybrary/databrary/volume.py
pybrary/databrary/types/__init__.py
pybrary/databrary/types/category.py
pybrary/databrary/types/ethnicity.py
pybrary/databrary/types/gender.py
pybrary/databrary/types/race.py
pybrary/databrary/types/reason.py
pybrary/databrary/types/release.py
pybrary/databrary/types/setting.py
pybrary/databrary/types/term.py
pybrary/utils/__init__.py
pybrary/utils/utils.py
pydatabrary-0.9.1.dist-info/LICENSE.txt
pydatabrary-0.9.1.dist-info/METADATA
pydatabrary-0.9.1.dist-info/WHEEL
pydatabrary-0.9.1.dist-info/top_level.txt
pydatabrary-0.9.1.dist-info/RECORD
