Metadata-Version: 2.1
Name: pydatabrary
Version: 0.9.1
Summary: Databrary API wrapper
Home-page: https://github.com/TheoWolf/pybrary
Author: Reda Nezzar
License: UNKNOWN
Platform: UNKNOWN
Classifier: Operating System :: OS Independent
Classifier: License :: OSI Approved :: MIT License
Classifier: Programming Language :: Python :: 3
Classifier: Programming Language :: Python :: 3.6
Classifier: Programming Language :: Python :: 3.8
License-File: LICENSE.txt
Requires-Dist: requests
Requires-Dist: pandas
Requires-Dist: jsonschema
